mrmd_ai/__init__.py
mrmd_ai/juice.py
mrmd_ai/server.py
mrmd_ai/metrics/__init__.py
mrmd_ai/modules/__init__.py
mrmd_ai/modules/code.py
mrmd_ai/modules/correct.py
mrmd_ai/modules/document.py
mrmd_ai/modules/edit.py
mrmd_ai/modules/finish.py
mrmd_ai/modules/fix.py
mrmd_ai/modules/notebook.py
mrmd_ai/modules/text.py
mrmd_ai/optimizers/__init__.py
mrmd_ai/signatures/__init__.py
mrmd_ai/signatures/code.py
mrmd_ai/signatures/correct.py
mrmd_ai/signatures/document.py
mrmd_ai/signatures/edit.py
mrmd_ai/signatures/finish.py
mrmd_ai/signatures/fix.py
mrmd_ai/signatures/notebook.py
mrmd_ai/signatures/text.py
mrmd_ai/utils/__init__.py
mrmd_ai-0.1.1.dist-info/METADATA
mrmd_ai-0.1.1.dist-info/WHEEL
mrmd_ai-0.1.1.dist-info/entry_points.txt
mrmd_ai-0.1.1.dist-info/RECORD
