Metadata-Version: 2.4
Name: mrmd-ai
Version: 0.1.1
Summary: AI programs for MRMD editor - completions, fixes, and corrections
Requires-Python: >=3.11
Requires-Dist: dspy>=2.6
Requires-Dist: fastapi>=0.115
Requires-Dist: litellm>=1.50
Requires-Dist: uvicorn>=0.32
